spade_artifact/__init__.py
spade_artifact/agent.py
spade_artifact/artifact.py
spade_artifact-0.3.1.dist-info/licenses/AUTHORS.rst
spade_artifact-0.3.1.dist-info/licenses/LICENSE
spade_artifact-0.3.1.dist-info/METADATA
spade_artifact-0.3.1.dist-info/WHEEL
spade_artifact-0.3.1.dist-info/top_level.txt
spade_artifact-0.3.1.dist-info/RECORD
