Metadata-Version: 2.4
Name: spade_artifact
Version: 0.3.1
Summary: Plugin for SPADE 3 to develop artifacts.
Home-page: https://github.com/javipalanca/spade_artifact
Author: Javi Palanca
Author-email: jpalanca@gmail.com
License: MIT license
Keywords: spade_artifact
Classifier: Development Status :: 2 - Pre-Alpha
Classifier: Intended Audience :: Developers
Classifier: License :: OSI Approved :: MIT License
Classifier: Natural Language :: English
Classifier: Programming Language :: Python :: 3
Classifier: Programming Language :: Python :: 3.9
Classifier: Programming Language :: Python :: 3.10
Classifier: Programming Language :: Python :: 3.11
Classifier: Programming Language :: Python :: 3.12
Requires-Python: >=3.8,<3.13
License-File: LICENSE
License-File: AUTHORS.rst
Requires-Dist: aiounittest==1.5.0
Requires-Dist: spade>=4.1.2
Requires-Dist: spade-pubsub>=0.3.0
Requires-Dist: pandas<3.0.0,>=2.0.3; python_version >= "3.8"
Requires-Dist: aiohttp<4.0.0,>=3.8.0
Requires-Dist: pymysql>=1.1.0
Requires-Dist: psycopg[binary]>=3.0.0
Requires-Dist: pymongo<5.0.0,>=4.6.3
Requires-Dist: motor<4.0.0,>=3.4.0
Requires-Dist: typing_extensions>=3.7.4; python_version < "3.9"
Dynamic: author
Dynamic: author-email
Dynamic: classifier
Dynamic: description
Dynamic: home-page
Dynamic: keywords
Dynamic: license
Dynamic: license-file
Dynamic: requires-dist
Dynamic: requires-python
Dynamic: summary
